synapse/ml/automl/BestModel.py
synapse/ml/automl/FindBestModel.py
synapse/ml/automl/HyperparamBuilder.py
synapse/ml/automl/TuneHyperparameters.py
synapse/ml/automl/TuneHyperparametersModel.py
synapse/ml/automl/_BestModel.py
synapse/ml/automl/_TuneHyperparametersModel.py
synapse/ml/automl/__init__.py
synapse/ml/causal/DiffInDiffEstimator.py
synapse/ml/causal/DiffInDiffModel.py
synapse/ml/causal/DoubleMLEstimator.py
synapse/ml/causal/DoubleMLModel.py
synapse/ml/causal/OrthoForestDMLEstimator.py
synapse/ml/causal/OrthoForestDMLModel.py
synapse/ml/causal/OrthoForestVariableTransformer.py
synapse/ml/causal/ResidualTransformer.py
synapse/ml/causal/SyntheticControlEstimator.py
synapse/ml/causal/SyntheticDiffInDiffEstimator.py
synapse/ml/causal/_DiffInDiffModel.py
synapse/ml/causal/_DoubleMLModel.py
synapse/ml/causal/__init__.py
synapse/ml/cntk/CNTKModel.py
synapse/ml/cntk/__init__.py
synapse/ml/cognitive/__init__.py
synapse/ml/cognitive/anomaly.py
synapse/ml/cognitive/bing.py
synapse/ml/cognitive/face.py
synapse/ml/cognitive/form.py
synapse/ml/cognitive/geospatial.py
synapse/ml/cognitive/langchain.py
synapse/ml/cognitive/language.py
synapse/ml/cognitive/openai.py
synapse/ml/cognitive/search.py
synapse/ml/cognitive/speech.py
synapse/ml/cognitive/text.py
synapse/ml/cognitive/translate.py
synapse/ml/cognitive/vision.py
synapse/ml/core/__init__.py
synapse/ml/core/init_spark.py
synapse/ml/core/logging/SynapseMLLogger.py
synapse/ml/core/logging/__init__.py
synapse/ml/core/platform/Platform.py
synapse/ml/core/platform/__init__.py
synapse/ml/core/schema/TypeConversionUtils.py
synapse/ml/core/schema/Utils.py
synapse/ml/core/schema/__init__.py
synapse/ml/core/serialize/__init__.py
synapse/ml/core/serialize/java_params_patch.py
synapse/ml/core/spark/FluentAPI.py
synapse/ml/core/spark/__init__.py
synapse/ml/core/spark/functions.py
synapse/ml/cyber/__init__.py
synapse/ml/cyber/dataset.py
synapse/ml/cyber/anomaly/__init__.py
synapse/ml/cyber/anomaly/collaborative_filtering.py
synapseml-1.1.2.dist-info/METADATA
synapseml-1.1.2.dist-info/WHEEL
synapseml-1.1.2.dist-info/top_level.txt
synapseml-1.1.2.dist-info/zip-safe
synapseml-1.1.2.dist-info/RECORD
