Metadata-Version: 2.4
Name: synapseml
Version: 1.1.2
Summary: Synapse Machine Learning
Home-page: https://github.com/Microsoft/SynapseML
Author: Microsoft
Author-email: synapseml-support@microsoft.com
License: MIT
Classifier: Development Status :: 4 - Beta
Classifier: Intended Audience :: Developers
Classifier: Intended Audience :: Science/Research
Classifier: Topic :: Software Development :: Libraries
Classifier: License :: OSI Approved :: MIT License
Classifier: Programming Language :: Python :: 2
Classifier: Programming Language :: Python :: 3
Dynamic: author
Dynamic: author-email
Dynamic: classifier
Dynamic: description
Dynamic: home-page
Dynamic: license
Dynamic: summary
